MANIFEST.in
README.rst
setup.py
django_multihostsettings.egg-info/PKG-INFO
django_multihostsettings.egg-info/SOURCES.txt
django_multihostsettings.egg-info/dependency_links.txt
django_multihostsettings.egg-info/top_level.txt
multihostsettings/__init__.py
multihostsettings/middleware.py